[
    {
        "name": "අනුරාධ ජයරත්න",
        "gender": "පුරුෂ",
        "birthday": "1985-12-22",
        "birth_year": 1985,
        "age": 36,
        "education": "මෙතුමා අධ්යාපනය ලබා ඇත්‍තේ \tTrinity College, Kandy; Royal College, Colombo;  යන පාසල්වලය.තම ප්‍රථම උපාධිය LLB, University of Buckingham ලබාගෙන ඇත. ඊට අමතරව PGDip, International Economy, University of Harvard  පශ්චාත් උපාධිය ද සම්පූර්ණ කර ඇත.",
        "position": "රාජ්‍ය අමාත්‍ය  ,  ග්‍රාමීය කුඹුරු හා ආශ්‍රිත වැව්, ජලාශ හා වාරිමාර්ග සංවර්ධන",
        "party": "ශ්‍රී ලංකා පොදුජන පෙරමුණ",
        "district": "මහනුවර",
        "contact_information": [
            "712724724 / 718009009",
            "anuradha_j@parliament.lk"
        ],
        "overall_rank": 148,
        "participated_in_parliament": 15,
        "related_subjects": [
            "ආණ්ඩුකරණ, පරිපාලන හා පාර්ලිමේන්තු කටයුතු",
            "නගර සැලසුම්, යටිතල පහසුකම් හා ප්‍රවාහන",
            "ස්වභාවික සම්පත් හා පරිසර",
            "ආර්ථික හා මුල්‍ය"
        ],
        "terms_in_parliament": "2020-08-20 සිට අද දක්වා ශ්‍රී ලංකා පොදුජන පෙරමුණ",
        "biography": "අනුරාධ ජයරත්න මහතා 1985-12-22 දින උපත ලබා ඇත.අනුරාධ ජයරත්න මහතාගේ වයස අවුරුදු 36කි.මෙතුමා අධ්යාපනය ලබා ඇත්‍තේ \tTrinity College, Kandy; Royal College, Colombo;  යන පාසල්වලය.තම ප්‍රථම උපාධිය LLB, University of Buckingham ලබාගෙන ඇත. ඊට අමතරව PGDip, International Economy, University of Harvard  පශ්චාත් උපාධිය ද සම්පූර්ණ කර ඇත.2020-08-20 සිට අද දක්වා ශ්‍රී ලංකා පොදුජන පෙරමුණ නියෝජනය කරමින් පාර්ලිමේන්තුවේ අසුන් ගෙන සිටී.අනුරාධ ජයරත්න මහතා 712724724 / 718009009, anuradha_j@parliament.lk,  මගින් සම්බන්ධකරගත හැකිය."
    }
]