[
    {
        "name": "ජෝන් සෙනෙවිරත්න",
        "gender": "පුරුෂ",
        "birthday": "1941-01-15",
        "birth_year": 1941,
        "age": 80,
        "education": "",
        "position": "පාර්ලිමේන්තු මන්ත්‍රී",
        "party": "ශ්‍රී ලංකා පොදුජන පෙරමුණ",
        "district": "රත්නපුර",
        "contact_information": [
            "112888112 / 773011588",
            "senevirathne_wdj@parliament.lk"
        ],
        "overall_rank": 147,
        "participated_in_parliament": 11,
        "related_subjects": [
            "ආර්ථික හා මුල්‍ය",
            "කම්කරු හා රැකියා",
            "වෙළඳ හා කර්මාන්ත",
            "ආණ්ඩුකරණ, පරිපාලන හා පාර්ලිමේන්තු කටයුතු",
            "යුක්තිය, ආරක්ෂාව හා මහජන සාමය"
        ],
        "terms_in_parliament": "2020-08-20 සිට අද දක්වා ශ්‍රී ලංකා පොදුජන පෙරමුණ",
        "biography": "ජෝන් සෙනෙවිරත්න මහතා 1941-01-15 දින උපත ලබා ඇත.ජෝන් සෙනෙවිරත්න මහතාගේ වයස අවුරුදු 80කි.2020-08-20 සිට අද දක්වා ශ්‍රී ලංකා පොදුජන පෙරමුණ නියෝජනය කරමින් පාර්ලිමේන්තුවේ අසුන් ගෙන සිටී.ජෝන් සෙනෙවිරත්න මහතා 112888112 / 773011588, senevirathne_wdj@parliament.lk,  මගින් සම්බන්ධකරගත හැකිය."
    }
]